{
    "placements": [
        {
            "x": 81.79179607904761,
            "y": 644.8039157663693
        },
        {
            "x": 157.8971243395924,
            "y": 690.7106496773089
        },
        {
            "x": 107.04731057614437,
            "y": 540.7689465776622
        },
        {
            "x": 110.24922204120655,
            "y": 674.0825855465891
        },
        {
            "x": 129.69873777018725,
            "y": 524.781487898708
        },
        {
            "x": 96.3554758389585,
            "y": 559.5647635171076
        },
        {
            "x": 150.10398347940716,
            "y": 535.4240048470253
        },
        {
            "x": 117.73013309103816,
            "y": 601.1795768204839
        },
        {
            "x": 143.60462387395688,
            "y": 522.566385403231
        },
        {
            "x": 84.40924126356114,
            "y": 628.1315862005566
        }
    ]
}