{
    "placements": [
        {
            "x": 685.7248784633003,
            "y": 347.33595229049024
        },
        {
            "x": 788.9447981822047,
            "y": 403.5044034768382
        },
        {
            "x": 669.9071639575563,
            "y": 376.72073530765283
        },
        {
            "x": 704.2491954356661,
            "y": 359.99778183130445
        },
        {
            "x": 736.3702543472732,
            "y": 449.3702024819191
        },
        {
            "x": 629.4394030936246,
            "y": 460.7123962509038
        },
        {
            "x": 734.4544059417464,
            "y": 434.98416948783404
        },
        {
            "x": 617.7090662721121,
            "y": 384.91426787521425
        },
        {
            "x": 767.7700270115258,
            "y": 366.1111692362983
        },
        {
            "x": 793.1743905098058,
            "y": 361.51504082629225
        },
        {
            "x": 781.0437401631119,
            "y": 474.2591134334258
        },
        {
            "x": 615.7917206742762,
            "y": 457.13544685213617
        },
        {
            "x": 621.0677008563968,
            "y": 403.63751668605835
        },
        {
            "x": 615.8023888714623,
            "y": 440.3149862677394
        },
        {
            "x": 786.4453387672293,
            "y": 383.14545131388377
        },
        {
            "x": 710.5449441306037,
            "y": 374.7969827772104
        },
        {
            "x": 628.3153035078734,
            "y": 341.5171551613683
        },
        {
            "x": 652.8143708071739,
            "y": 454.3402150335443
        },
        {
            "x": 739.9661280196002,
            "y": 466.61275718622505
        },
        {
            "x": 788.3346779022062,
            "y": 435.8446380751416
        },
        {
            "x": 750.5519090558179,
            "y": 377.0412272475852
        },
        {
            "x": 634.5569549456969,
            "y": 373.7924211811239
        },
        {
            "x": 669.5611360085015,
            "y": 435.24563391424977
        },
        {
            "x": 720.7654037851679,
            "y": 437.18018116251574
        },
        {
            "x": 638.3110792056243,
            "y": 398.99048603977565
        },
        {
            "x": 724.5107486539105,
            "y": 451.05995315595527
        },
        {
            "x": 641.6534182050514,
            "y": 472.98140842094153
        },
        {
            "x": 661.8020344897183,
            "y": 347.15993036802854
        },
        {
            "x": 651.6446710641704,
            "y": 469.75990409439424
        },
        {
            "x": 762.1877630838136,
            "y": 424.18002970664764
        },
        {
            "x": 757.3554747567305,
            "y": 436.6685548125154
        },
        {
            "x": 728.2818557882131,
            "y": 403.6470678554136
        },
        {
            "x": 631.7317718717883,
            "y": 450.9685598732757
        },
        {
            "x": 806.7094273658979,
            "y": 435.56258152917144
        },
        {
            "x": 678.1792927976601,
            "y": 411.33505530205326
        },
        {
            "x": 731.206293932724,
            "y": 416.94435685684175
        },
        {
            "x": 653.0786881475144,
            "y": 437.5517806953526
        },
        {
            "x": 630.4094090561426,
            "y": 475.04523255585
        },
        {
            "x": 673.0237501119374,
            "y": 343.3927754230764
        },
        {
            "x": 712.3797280338498,
            "y": 400.41028382229166
        },
        {
            "x": 698.7612838259718,
            "y": 428.39545463556215
        },
        {
            "x": 624.3676301708294,
            "y": 433.0798642952367
        },
        {
            "x": 808.0690656463006,
            "y": 401.06772283095296
        },
        {
            "x": 618.0789909866076,
            "y": 472.5009123755158
        },
        {
            "x": 670.2463026317984,
            "y": 397.7095547116872
        },
        {
            "x": 773.8918877145703,
            "y": 456.739950261889
        },
        {
            "x": 737.114782081039,
            "y": 357.1409458276541
        },
        {
            "x": 753.5562838476878,
            "y": 367.44778141679603
        },
        {
            "x": 780.5450786247594,
            "y": 412.1886566985346
        },
        {
            "x": 709.159188380539,
            "y": 441.91016617273453
        },
        {
            "x": 645.3664847083234,
            "y": 420.84259589195375
        },
        {
            "x": 728.2452119222121,
            "y": 468.160169314202
        },
        {
            "x": 681.8592955553249,
            "y": 450.67681284140644
        },
        {
            "x": 798.0087181483436,
            "y": 459.4243168823534
        },
        {
            "x": 767.9725291039667,
            "y": 399.7313709644281
        },
        {
            "x": 627.8526927991085,
            "y": 359.38336959964755
        },
        {
            "x": 808.7992552084845,
            "y": 351.71644444145096
        },
        {
            "x": 615.9750234936248,
            "y": 341.66516259343604
        },
        {
            "x": 655.6146517803961,
            "y": 390.75753236643857
        },
        {
            "x": 716.6426110820112,
            "y": 474.2630328113506
        },
        {
            "x": 779.6173360536887,
            "y": 398.65885672981796
        },
        {
            "x": 767.8005248637872,
            "y": 340.80994500769765
        },
        {
            "x": 798.6945130008713,
            "y": 338.3040557230376
        },
        {
            "x": 796.4996877617667,
            "y": 371.33777033087694
        },
        {
            "x": 705.3209630210516,
            "y": 346.875192712003
        },
        {
            "x": 761.4914317263716,
            "y": 452.7515794205254
        },
        {
            "x": 702.7609619450574,
            "y": 470.8572418381726
        },
        {
            "x": 753.7210408010153,
            "y": 402.3622503976162
        },
        {
            "x": 722.2099374370696,
            "y": 347.34937635546055
        },
        {
            "x": 771.8526946612878,
            "y": 376.0436097695695
        }
    ]
}